{
    "cloudflare": {
        "apitoken": "$CLOUDFLARE_API_TOKEN"
    },
    "azuredns_main": {
        "SubscriptionID": "69111246-db23-463c-82b2-7815ed5f8a1a",
        "ResourceGroup": "zhp-dns",
        "TenantID": "e1368d1e-3975-4ce6-893d-fc351fd44dcd",
        "ClientID": "e5bcc5f9-8cab-4fac-8278-ac2a7c77f02e",
        "ClientSecret": "$AZURE_DNS_MANAGEMENT_CREDENTIALS"
    },
    "ovh":{
        "app-key": "qP8GPONKwzHovsF8",
        "app-secret-key": "$OVH_APP_SECRET_KEY",
        "consumer-key": "$OVH_CONSUMER_KEY"
      }
}
